dcfgrpc/__init__.py
dcfgrpc/api.py
dcfgrpc/gateway_pb2.py
dcfgrpc/gateway_pb2_grpc.py
dcfgrpc-0.1.3.dist-info/LICENSE
dcfgrpc-0.1.3.dist-info/METADATA
dcfgrpc-0.1.3.dist-info/WHEEL
dcfgrpc-0.1.3.dist-info/top_level.txt
dcfgrpc-0.1.3.dist-info/RECORD
