Metadata-Version: 2.1
Name: dcfgrpc
Version: 0.1.3
Summary: DCF API for gRPC
Home-page: https://github.com/DigitalCompanion-KETI
Author: cyy03576
Author-email: cyy03576@keti.re.kr
License: MIT
Platform: UNKNOWN
Classifier: License :: OSI Approved :: MIT License
Requires-Python: >=2.7,!=3.0.*,!=3.1.*,!=3.2.*,!=3.3.*
Requires-Dist: grpcio-tools (>=1.17.1)
